{
    "0": [
        "06:00",
        "06:08",
        "06:16",
        "06:24",
        "06:33",
        "06:41",
        "06:50",
        "06:58",
        "07:07",
        "07:15",
        "07:23",
        "07:32",
        "07:41",
        "07:49",
        "07:57",
        "08:06",
        "08:15",
        "08:23",
        "08:31",
        "08:39",
        "08:48",
        "08:58",
        "09:07",
        "09:16",
        "09:27",
        "09:34",
        "09:42",
        "09:50",
        "09:57",
        "10:05",
        "10:14",
        "10:22",
        "10:31",
        "10:40",
        "10:47",
        "10:53",
        "10:59",
        "11:05",
        "11:13",
        "11:22",
        "11:30",
        "11:38",
        "11:47",
        "11:56",
        "12:04",
        "12:13",
        "12:21",
        "12:30",
        "12:38",
        "12:47",
        "12:55",
        "13:04",
        "13:13",
        "13:22",
        "13:29",
        "13:38",
        "13:46",
        "13:54",
        "14:03",
        "14:12",
        "14:20",
        "14:29",
        "14:37",
        "14:46",
        "14:54",
        "15:03",
        "15:12",
        "15:14",
        "15:21",
        "15:29",
        "15:41",
        "15:46",
        "15:53",
        "16:02",
        "16:11",
        "16:19",
        "16:28",
        "16:36",
        "16:46",
        "16:53",
        "17:02",
        "17:11",
        "17:19",
        "17:27",
        "17:36",
        "17:44",
        "17:52",
        "18:01",
        "18:10",
        "18:18",
        "18:27",
        "18:35",
        "18:44",
        "18:52",
        "19:01",
        "19:09",
        "19:18",
        "19:26",
        "19:35",
        "19:43",
        "19:51",
        "20:00",
        "20:09",
        "20:18",
        "20:28",
        "20:37",
        "20:46",
        "20:56",
        "21:06",
        "21:15",
        "21:26",
        "21:37",
        "21:48",
        "21:59",
        "22:13",
        "22:27",
        "22:40",
        "22:46",
        "22:52",
        "23:06",
        "23:21"
    ],
    "1": [
        "06:35",
        "06:45",
        "06:54",
        "07:03",
        "07:11",
        "07:20",
        "07:28",
        "07:37",
        "07:46",
        "07:54",
        "08:03",
        "08:11",
        "08:20",
        "08:28",
        "08:37",
        "08:45",
        "08:54",
        "09:02",
        "09:10",
        "09:19",
        "09:27",
        "09:36",
        "09:44",
        "09:53",
        "10:02",
        "10:10",
        "10:18",
        "10:28",
        "10:39",
        "10:44",
        "10:50",
        "11:01",
        "11:09",
        "11:18",
        "11:26",
        "11:35",
        "11:43",
        "11:51",
        "11:59",
        "12:08",
        "12:18",
        "12:26",
        "12:35",
        "12:43",
        "12:52",
        "13:00",
        "13:09",
        "13:17",
        "13:26",
        "13:34",
        "13:42",
        "13:51",
        "13:59",
        "14:08",
        "14:16",
        "14:26",
        "14:34",
        "14:42",
        "14:50",
        "14:59",
        "15:07",
        "15:16",
        "15:25",
        "15:33",
        "15:42",
        "15:50",
        "15:58",
        "16:06",
        "16:15",
        "16:26",
        "16:32",
        "16:41",
        "16:50",
        "16:59",
        "17:07",
        "17:15",
        "17:24",
        "17:32",
        "17:41",
        "17:49",
        "17:57",
        "18:00",
        "18:06",
        "18:14",
        "18:23",
        "18:31",
        "18:40",
        "18:49",
        "18:58",
        "19:06",
        "19:14",
        "19:23",
        "19:31",
        "19:40",
        "19:48",
        "19:57",
        "20:05",
        "20:14",
        "20:22",
        "20:30",
        "20:39",
        "20:47",
        "20:58",
        "21:10",
        "21:21",
        "21:31",
        "21:43",
        "21:55",
        "22:07",
        "22:21",
        "22:35",
        "22:48",
        "23:03",
        "23:18"
    ],
    "2": [],
    "3": [],
    "4": [
        "09:25",
        "15:12"
    ],
    "5": [
        "10:27",
        "16:14"
    ],
    "6": [],
    "7": [],
    "8": [],
    "9": [
        "15:37"
    ]
}